platemotion/__init__.py
platemotion/classes/__init__.py
platemotion/classes/plate.py
platemotion/data/.DS_Store
platemotion/data/NNR_GSRMv2.1.csv
platemotion/data/NNR_MRV56.csv
platemotion/data/README.txt
platemotion/data/NnrGSRMv2.1_PltBndsLatLon/.DS_Store
platemotion/data/NnrGSRMv2.1_PltBndsLatLon/AF
platemotion/data/NnrGSRMv2.1_PltBndsLatLon/AM
platemotion/data/NnrGSRMv2.1_PltBndsLatLon/AN
platemotion/data/NnrGSRMv2.1_PltBndsLatLon/AR
platemotion/data/NnrGSRMv2.1_PltBndsLatLon/AS
platemotion/data/NnrGSRMv2.1_PltBndsLatLon/AU
platemotion/data/NnrGSRMv2.1_PltBndsLatLon/BC
platemotion/data/NnrGSRMv2.1_PltBndsLatLon/BG
platemotion/data/NnrGSRMv2.1_PltBndsLatLon/BU
platemotion/data/NnrGSRMv2.1_PltBndsLatLon/CA
platemotion/data/NnrGSRMv2.1_PltBndsLatLon/CL
platemotion/data/NnrGSRMv2.1_PltBndsLatLon/CO
platemotion/data/NnrGSRMv2.1_PltBndsLatLon/CP
platemotion/data/NnrGSRMv2.1_PltBndsLatLon/DA
platemotion/data/NnrGSRMv2.1_PltBndsLatLon/EA
platemotion/data/NnrGSRMv2.1_PltBndsLatLon/EU
platemotion/data/NnrGSRMv2.1_PltBndsLatLon/GP
platemotion/data/NnrGSRMv2.1_PltBndsLatLon/GSRM_plate_outlines.gmt
platemotion/data/NnrGSRMv2.1_PltBndsLatLon/GV
platemotion/data/NnrGSRMv2.1_PltBndsLatLon/IN
platemotion/data/NnrGSRMv2.1_PltBndsLatLon/JF
platemotion/data/NnrGSRMv2.1_PltBndsLatLon/JZ
platemotion/data/NnrGSRMv2.1_PltBndsLatLon/LW
platemotion/data/NnrGSRMv2.1_PltBndsLatLon/MA
platemotion/data/NnrGSRMv2.1_PltBndsLatLon/NA
platemotion/data/NnrGSRMv2.1_PltBndsLatLon/NB
platemotion/data/NnrGSRMv2.1_PltBndsLatLon/NI
platemotion/data/NnrGSRMv2.1_PltBndsLatLon/NZ
platemotion/data/NnrGSRMv2.1_PltBndsLatLon/OK
platemotion/data/NnrGSRMv2.1_PltBndsLatLon/ON
platemotion/data/NnrGSRMv2.1_PltBndsLatLon/PA
platemotion/data/NnrGSRMv2.1_PltBndsLatLon/PM
platemotion/data/NnrGSRMv2.1_PltBndsLatLon/PR
platemotion/data/NnrGSRMv2.1_PltBndsLatLon/PS
platemotion/data/NnrGSRMv2.1_PltBndsLatLon/RI
platemotion/data/NnrGSRMv2.1_PltBndsLatLon/RO
platemotion/data/NnrGSRMv2.1_PltBndsLatLon/SA
platemotion-0.1.7.dist-info/LICENSE.txt
platemotion-0.1.7.dist-info/METADATA
platemotion-0.1.7.dist-info/WHEEL
platemotion-0.1.7.dist-info/top_level.txt
platemotion-0.1.7.dist-info/RECORD
