Metadata-Version: 2.1
Name: platemotion
Version: 0.1.7
Summary: A package to handle the tectonic plate motion
Home-page: https://github.com/lcx366/PlateTectonic
Author: Chunxiao Li
Author-email: lcx366@126.com
License: MIT
Keywords: tectonic plate,plate motion,nnr-morvel56,gsrmv2.1,itrf2014
Platform: UNKNOWN
Classifier: Development Status :: 4 - Beta
Classifier: Intended Audience :: Education
Classifier: Intended Audience :: Science/Research
Classifier: Programming Language :: Python :: 3.8
Classifier: Programming Language :: Python :: 3.9
Classifier: License :: OSI Approved :: MIT License
Requires-Python: >=3.8
Requires-Dist: numpy
Requires-Dist: scipy
Requires-Dist: matplotlib
Requires-Dist: astropy
Requires-Dist: pandas
Requires-Dist: xarray
Requires-Dist: sphericalpolygon
Provides-Extra: colored-progress
Requires-Dist: tqdm ; extra == 'colored-progress'
Requires-Dist: colorama ; extra == 'colored-progress'
Provides-Extra: download
Requires-Dist: ftplib ; extra == 'download'
Requires-Dist: requests ; extra == 'download'
Provides-Extra: files
Requires-Dist: pkg-resources ; extra == 'files'
Requires-Dist: os ; extra == 'files'
Requires-Dist: pathlib ; extra == 'files'
Requires-Dist: gzip ; extra == 'files'
Requires-Dist: zipfile ; extra == 'files'
Provides-Extra: other
Requires-Dist: datetime ; extra == 'other'
Requires-Dist: time ; extra == 'other'
